{
  "schema_version": "market-facts/v1",
  "ticker": "GAA",
  "asset_type": "etf",
  "generated_at": "2026-07-09T02:27:20Z",
  "identity": {
    "name": "GAA",
    "exchange": null,
    "currency": null,
    "sector": null,
    "industry": null,
    "fund_family": null,
    "category": null
  },
  "facts": {
    "price": {
      "value": 35.0345,
      "source": "stockanalysis.quote",
      "as_of": null,
      "fetched_at": "2026-06-19T09:06:43Z",
      "confidence": "observed",
      "policy": [
        "yf",
        "yf.fast_info",
        "stockanalysis.quote",
        "yf.stockanalysis_fallback.quote",
        "slickcharts"
      ],
      "candidates": [
        {
          "value": 35.0345,
          "source": "stockanalysis.quote",
          "as_of": null,
          "fetched_at": "2026-06-19T09:06:43Z",
          "confidence": "observed"
        }
      ],
      "candidate_count": 1
    },
    "previous_close": {
      "value": 35.03,
      "source": "stockanalysis.quote",
      "as_of": null,
      "fetched_at": "2026-06-19T09:06:43Z",
      "confidence": "observed",
      "policy": [
        "yf",
        "stockanalysis.quote",
        "yf.stockanalysis_fallback.quote"
      ],
      "candidates": [
        {
          "value": 35.03,
          "source": "stockanalysis.quote",
          "as_of": null,
          "fetched_at": "2026-06-19T09:06:43Z",
          "confidence": "observed"
        }
      ],
      "candidate_count": 1
    },
    "change": {
      "value": 0.04,
      "source": "stockanalysis.quote",
      "as_of": null,
      "fetched_at": "2026-06-19T09:06:43Z",
      "confidence": "observed",
      "policy": [
        "stockanalysis.quote",
        "yf",
        "yf.derived",
        "yf.stockanalysis_fallback.quote"
      ],
      "candidates": [
        {
          "value": 0.04,
          "source": "stockanalysis.quote",
          "as_of": null,
          "fetched_at": "2026-06-19T09:06:43Z",
          "confidence": "observed"
        }
      ],
      "candidate_count": 1
    },
    "change_pct": {
      "value": 0.13,
      "source": "stockanalysis.quote",
      "as_of": null,
      "fetched_at": "2026-06-19T09:06:43Z",
      "confidence": "observed",
      "policy": [
        "stockanalysis.quote",
        "yf",
        "yf.derived",
        "yf.stockanalysis_fallback.quote"
      ],
      "candidates": [
        {
          "value": 0.13,
          "source": "stockanalysis.quote",
          "as_of": null,
          "fetched_at": "2026-06-19T09:06:43Z",
          "confidence": "observed"
        }
      ],
      "candidate_count": 1
    },
    "total_assets": {
      "value": 70820000.0,
      "source": "stockanalysis.overview",
      "as_of": null,
      "fetched_at": "2026-06-19T09:06:43Z",
      "confidence": "observed",
      "policy": [
        "yf",
        "stockanalysis.overview",
        "yf.stockanalysis_fallback.overview"
      ],
      "candidates": [
        {
          "value": 70820000.0,
          "source": "stockanalysis.overview",
          "as_of": null,
          "fetched_at": "2026-06-19T09:06:43Z",
          "confidence": "observed"
        }
      ],
      "candidate_count": 1
    },
    "dividend_yield": {
      "value": 3.61,
      "source": "stockanalysis.overview",
      "as_of": null,
      "fetched_at": "2026-06-19T09:06:43Z",
      "confidence": "observed",
      "unit": "percent_points",
      "policy": [
        "yf",
        "stockanalysis.overview",
        "yf.stockanalysis_fallback.overview",
        "slickcharts"
      ],
      "candidates": [
        {
          "value": 3.61,
          "source": "stockanalysis.overview",
          "as_of": null,
          "fetched_at": "2026-06-19T09:06:43Z",
          "confidence": "observed",
          "unit": "percent_points"
        }
      ],
      "candidate_count": 1
    },
    "beta": {
      "value": 0.48,
      "source": "stockanalysis.overview",
      "as_of": null,
      "fetched_at": "2026-06-19T09:06:43Z",
      "confidence": "observed",
      "policy": [
        "yf",
        "stockanalysis.overview",
        "yf.stockanalysis_fallback.overview"
      ],
      "candidates": [
        {
          "value": 0.48,
          "source": "stockanalysis.overview",
          "as_of": null,
          "fetched_at": "2026-06-19T09:06:43Z",
          "confidence": "observed"
        }
      ],
      "candidate_count": 1
    },
    "expense_ratio": {
      "value": 0.4,
      "source": "stockanalysis.overview",
      "as_of": null,
      "fetched_at": "2026-06-19T09:06:43Z",
      "confidence": "observed",
      "unit": "percent_points",
      "policy": [
        "yf",
        "stockanalysis.overview",
        "yf.stockanalysis_fallback.overview"
      ],
      "candidates": [
        {
          "value": 0.4,
          "source": "stockanalysis.overview",
          "as_of": null,
          "fetched_at": "2026-06-19T09:06:43Z",
          "confidence": "observed",
          "unit": "percent_points"
        }
      ],
      "candidate_count": 1
    },
    "return_1m": {
      "value": 0.8109,
      "source": "stockanalysis.detail.performance",
      "as_of": null,
      "fetched_at": "2026-06-19T09:06:43Z",
      "confidence": "observed",
      "unit": "percent_points",
      "policy": [
        "yf.history_1y",
        "stockanalysis.detail.performance",
        "stockanalysis.etf_screener.performance",
        "stockanalysis.etf_universe.performance"
      ],
      "candidates": [
        {
          "value": 0.8109,
          "source": "stockanalysis.detail.performance",
          "as_of": null,
          "fetched_at": "2026-06-19T09:06:43Z",
          "confidence": "observed",
          "unit": "percent_points"
        },
        {
          "value": 0.8109,
          "source": "stockanalysis.etf_screener.performance",
          "as_of": null,
          "fetched_at": "2026-07-09T02:22:42Z",
          "confidence": "observed",
          "unit": "percent_points"
        }
      ],
      "candidate_count": 2
    },
    "return_3m": {
      "value": 4.948357990832888,
      "source": "stockanalysis.detail.history",
      "as_of": "2026-06-18",
      "fetched_at": "2026-06-19T09:06:43Z",
      "confidence": "derived",
      "unit": "percent_points",
      "policy": [
        "yf.history_1y",
        "stockanalysis.detail.history"
      ],
      "candidates": [
        {
          "value": 4.948357990832888,
          "source": "stockanalysis.detail.history",
          "as_of": "2026-06-18",
          "fetched_at": "2026-06-19T09:06:43Z",
          "confidence": "derived",
          "unit": "percent_points"
        }
      ],
      "candidate_count": 1
    },
    "return_ytd": {
      "value": 8.796,
      "source": "stockanalysis.detail.performance",
      "as_of": null,
      "fetched_at": "2026-06-19T09:06:43Z",
      "confidence": "observed",
      "unit": "percent_points",
      "policy": [
        "yf.history_1y",
        "stockanalysis.detail.performance",
        "stockanalysis.etf_screener.performance",
        "stockanalysis.etf_universe.performance",
        "yf"
      ],
      "candidates": [
        {
          "value": 8.796,
          "source": "stockanalysis.detail.performance",
          "as_of": null,
          "fetched_at": "2026-06-19T09:06:43Z",
          "confidence": "observed",
          "unit": "percent_points"
        },
        {
          "value": 8.796,
          "source": "stockanalysis.etf_screener.performance",
          "as_of": null,
          "fetched_at": "2026-07-09T02:22:42Z",
          "confidence": "observed",
          "unit": "percent_points"
        }
      ],
      "candidate_count": 2
    },
    "return_1y": {
      "value": 20.093,
      "source": "stockanalysis.detail.performance",
      "as_of": null,
      "fetched_at": "2026-06-19T09:06:43Z",
      "confidence": "observed",
      "unit": "percent_points",
      "policy": [
        "yf.history_1y",
        "stockanalysis.detail.performance",
        "stockanalysis.etf_screener.performance",
        "stockanalysis.etf_universe.performance",
        "yf"
      ],
      "candidates": [
        {
          "value": 20.093,
          "source": "stockanalysis.detail.performance",
          "as_of": null,
          "fetched_at": "2026-06-19T09:06:43Z",
          "confidence": "observed",
          "unit": "percent_points"
        },
        {
          "value": 20.093,
          "source": "stockanalysis.etf_screener.performance",
          "as_of": null,
          "fetched_at": "2026-07-09T02:22:42Z",
          "confidence": "observed",
          "unit": "percent_points"
        }
      ],
      "candidate_count": 2
    },
    "return_3y_avg": {
      "value": 6.42007022329818,
      "source": "stockanalysis.detail.history",
      "as_of": "2026-06-01",
      "fetched_at": "2026-06-19T09:06:43Z",
      "confidence": "derived",
      "unit": "percent_points",
      "policy": [
        "yf",
        "stockanalysis.detail.history"
      ],
      "candidates": [
        {
          "value": 6.42007022329818,
          "source": "stockanalysis.detail.history",
          "as_of": "2026-06-01",
          "fetched_at": "2026-06-19T09:06:43Z",
          "confidence": "derived",
          "unit": "percent_points"
        }
      ],
      "candidate_count": 1
    },
    "return_5y_avg": {
      "value": 6.648,
      "source": "stockanalysis.detail.performance",
      "as_of": null,
      "fetched_at": "2026-06-19T09:06:43Z",
      "confidence": "observed",
      "unit": "percent_points",
      "policy": [
        "yf",
        "stockanalysis.detail.performance",
        "stockanalysis.etf_screener.performance",
        "stockanalysis.etf_universe.performance"
      ],
      "candidates": [
        {
          "value": 6.648,
          "source": "stockanalysis.detail.performance",
          "as_of": null,
          "fetched_at": "2026-06-19T09:06:43Z",
          "confidence": "observed",
          "unit": "percent_points"
        },
        {
          "value": 6.648,
          "source": "stockanalysis.etf_screener.performance",
          "as_of": null,
          "fetched_at": "2026-07-09T02:22:42Z",
          "confidence": "observed",
          "unit": "percent_points"
        }
      ],
      "candidate_count": 2
    },
    "return_10y_avg": {
      "value": 7.664,
      "source": "stockanalysis.detail.performance",
      "as_of": null,
      "fetched_at": "2026-06-19T09:06:43Z",
      "confidence": "observed",
      "unit": "percent_points",
      "policy": [
        "stockanalysis.detail.performance",
        "stockanalysis.etf_screener.performance",
        "stockanalysis.etf_universe.performance"
      ],
      "candidates": [
        {
          "value": 7.664,
          "source": "stockanalysis.detail.performance",
          "as_of": null,
          "fetched_at": "2026-06-19T09:06:43Z",
          "confidence": "observed",
          "unit": "percent_points"
        },
        {
          "value": 7.664,
          "source": "stockanalysis.etf_screener.performance",
          "as_of": null,
          "fetched_at": "2026-07-09T02:22:42Z",
          "confidence": "observed",
          "unit": "percent_points"
        }
      ],
      "candidate_count": 2
    },
    "return_max_avg": {
      "value": 6.52,
      "source": "stockanalysis.detail.performance",
      "as_of": null,
      "fetched_at": "2026-06-19T09:06:43Z",
      "confidence": "observed",
      "unit": "percent_points",
      "policy": [
        "stockanalysis.detail.performance",
        "stockanalysis.etf_screener.performance",
        "stockanalysis.etf_universe.performance"
      ],
      "candidates": [
        {
          "value": 6.52,
          "source": "stockanalysis.detail.performance",
          "as_of": null,
          "fetched_at": "2026-06-19T09:06:43Z",
          "confidence": "observed",
          "unit": "percent_points"
        },
        {
          "value": 6.52,
          "source": "stockanalysis.etf_screener.performance",
          "as_of": null,
          "fetched_at": "2026-07-09T02:22:42Z",
          "confidence": "observed",
          "unit": "percent_points"
        }
      ],
      "candidate_count": 2
    }
  },
  "etf": {
    "holdings_count": 31,
    "holdings_updated": "Jun 15, 2026",
    "top_holdings": [
      {
        "rank": 1,
        "symbol": "#EYLD",
        "name": "Cambria Emerging Shareholder Yield ETF",
        "weight_pct": 11.08,
        "shares": 164725,
        "raw": {
          "no": 1,
          "n": "Cambria Emerging Shareholder Yield ETF",
          "s": "#EYLD",
          "as": "11.08%",
          "sh": "164,725"
        }
      },
      {
        "rank": 2,
        "symbol": "#GVAL",
        "name": "Cambria Global Value ETF",
        "weight_pct": 7.16,
        "shares": 137693,
        "raw": {
          "no": 2,
          "n": "Cambria Global Value ETF",
          "s": "#GVAL",
          "as": "7.16%",
          "sh": "137,693"
        }
      },
      {
        "rank": 3,
        "symbol": "#FYLD",
        "name": "Cambria Foreign Shareholder Yield ETF",
        "weight_pct": 7.06,
        "shares": 132677,
        "raw": {
          "no": 3,
          "n": "Cambria Foreign Shareholder Yield ETF",
          "s": "#FYLD",
          "as": "7.06%",
          "sh": "132,677"
        }
      },
      {
        "rank": 4,
        "symbol": "#BLDG",
        "name": "Cambria Global Real Estate ETF",
        "weight_pct": 6.53,
        "shares": 176896,
        "raw": {
          "no": 4,
          "n": "Cambria Global Real Estate ETF",
          "s": "#BLDG",
          "as": "6.53%",
          "sh": "176,896"
        }
      },
      {
        "rank": 5,
        "symbol": "#TYLD",
        "name": "Cambria Tactical Yield ETF",
        "weight_pct": 4.98,
        "shares": 142295,
        "raw": {
          "no": 5,
          "n": "Cambria Tactical Yield ETF",
          "s": "#TYLD",
          "as": "4.98%",
          "sh": "142,295"
        }
      },
      {
        "rank": 6,
        "symbol": "#QMOM",
        "name": "Alpha Architect U.S. Quantitative Momentum ETF",
        "weight_pct": 4.43,
        "shares": 40273,
        "raw": {
          "no": 6,
          "n": "Alpha Architect U.S. Quantitative Momentum ETF",
          "s": "#QMOM",
          "as": "4.43%",
          "sh": "40,273"
        }
      },
      {
        "rank": 7,
        "symbol": "#SYLD",
        "name": "Cambria Shareholder Yield ETF",
        "weight_pct": 4.26,
        "shares": 38589,
        "raw": {
          "no": 7,
          "n": "Cambria Shareholder Yield ETF",
          "s": "#SYLD",
          "as": "4.26%",
          "sh": "38,589"
        }
      },
      {
        "rank": 8,
        "symbol": "#BNDX",
        "name": "Vanguard Total International Bond ETF",
        "weight_pct": 4.08,
        "shares": 61315,
        "raw": {
          "no": 8,
          "n": "Vanguard Total International Bond ETF",
          "s": "#BNDX",
          "as": "4.08%",
          "sh": "61,315"
        }
      },
      {
        "rank": 9,
        "symbol": "#VAMO",
        "name": "Cambria Value & Momentum ETF",
        "weight_pct": 3.99,
        "shares": 81159,
        "raw": {
          "no": 9,
          "n": "Cambria Value & Momentum ETF",
          "s": "#VAMO",
          "as": "3.99%",
          "sh": "81,159"
        }
      },
      {
        "rank": 10,
        "symbol": "#CERY",
        "name": "State Street SPDR Bloomberg Enhanced Roll Yield Commodity Strategy No K-1 ETF",
        "weight_pct": 3.82,
        "shares": 78999,
        "raw": {
          "no": 10,
          "n": "State Street SPDR Bloomberg Enhanced Roll Yield Commodity Strategy No K-1 ETF",
          "s": "#CERY",
          "as": "3.82%",
          "sh": "78,999"
        }
      },
      {
        "rank": 11,
        "symbol": "#SDCI",
        "name": "USCF SummerHaven Dynamic Commodity Strategy No K-1 Fund",
        "weight_pct": 3.79,
        "shares": 102045,
        "raw": {
          "no": 11,
          "n": "USCF SummerHaven Dynamic Commodity Strategy No K-1 Fund",
          "s": "#SDCI",
          "as": "3.79%",
          "sh": "102,045"
        }
      },
      {
        "rank": 12,
        "symbol": "#HYEM",
        "name": "VanEck Emerging Markets High Yield Bond ETF",
        "weight_pct": 3.48,
        "shares": 124897,
        "raw": {
          "no": 12,
          "n": "VanEck Emerging Markets High Yield Bond ETF",
          "s": "#HYEM",
          "as": "3.48%",
          "sh": "124,897"
        }
      },
      {
        "rank": 13,
        "symbol": "#BND",
        "name": "Vanguard Total Bond Market ETF",
        "weight_pct": 3.36,
        "shares": 33221,
        "raw": {
          "no": 13,
          "n": "Vanguard Total Bond Market ETF",
          "s": "#BND",
          "as": "3.36%",
          "sh": "33,221"
        }
      },
      {
        "rank": 14,
        "symbol": "#BAR",
        "name": "GraniteShares Gold Shares",
        "weight_pct": 3.22,
        "shares": 54893,
        "raw": {
          "no": 14,
          "n": "GraniteShares Gold Shares",
          "s": "#BAR",
          "as": "3.22%",
          "sh": "54,893"
        }
      },
      {
        "rank": 15,
        "symbol": "#JPMB",
        "name": "JPMorgan USD Emerging Markets Sovereign Bond ETF",
        "weight_pct": 2.67,
        "shares": 47936,
        "raw": {
          "no": 15,
          "n": "JPMorgan USD Emerging Markets Sovereign Bond ETF",
          "s": "#JPMB",
          "as": "2.67%",
          "sh": "47,936"
        }
      },
      {
        "rank": 16,
        "symbol": "#EMLC",
        "name": "VanEck J. P. Morgan EM Local Currency Bond ETF",
        "weight_pct": 2.64,
        "shares": 74213,
        "raw": {
          "no": 16,
          "n": "VanEck J. P. Morgan EM Local Currency Bond ETF",
          "s": "#EMLC",
          "as": "2.64%",
          "sh": "74,213"
        }
      },
      {
        "rank": 17,
        "symbol": "#VCIT",
        "name": "Vanguard Intermediate-Term Corporate Bond ETF",
        "weight_pct": 2.54,
        "shares": 22349,
        "raw": {
          "no": 17,
          "n": "Vanguard Intermediate-Term Corporate Bond ETF",
          "s": "#VCIT",
          "as": "2.54%",
          "sh": "22,349"
        }
      },
      {
        "rank": 18,
        "symbol": "#SCHP",
        "name": "Schwab US TIPS ETF",
        "weight_pct": 2.5,
        "shares": 68282,
        "raw": {
          "no": 18,
          "n": "Schwab US TIPS ETF",
          "s": "#SCHP",
          "as": "2.50%",
          "sh": "68,282"
        }
      },
      {
        "rank": 19,
        "symbol": "#IMOM",
        "name": "Alpha Architect International Quantitative Momentum ETF",
        "weight_pct": 2.45,
        "shares": 39860,
        "raw": {
          "no": 19,
          "n": "Alpha Architect International Quantitative Momentum ETF",
          "s": "#IMOM",
          "as": "2.45%",
          "sh": "39,860"
        }
      },
      {
        "rank": 20,
        "symbol": "#MYLD",
        "name": "Cambria Micro and SmallCap Shareholder Yield ETF",
        "weight_pct": 2.34,
        "shares": 54085,
        "raw": {
          "no": 20,
          "n": "Cambria Micro and SmallCap Shareholder Yield ETF",
          "s": "#MYLD",
          "as": "2.34%",
          "sh": "54,085"
        }
      },
      {
        "rank": 21,
        "symbol": "#LYLD",
        "name": "Cambria Large Cap Shareholder Yield ETF",
        "weight_pct": 2.02,
        "shares": 48202,
        "raw": {
          "no": 21,
          "n": "Cambria Large Cap Shareholder Yield ETF",
          "s": "#LYLD",
          "as": "2.02%",
          "sh": "48,202"
        }
      },
      {
        "rank": 22,
        "symbol": "#WIP",
        "name": "State Street SPDR FTSE International Government Inflation-Protected Bond ETF",
        "weight_pct": 1.73,
        "shares": 31307,
        "raw": {
          "no": 22,
          "n": "State Street SPDR FTSE International Government Inflation-Protected Bond ETF",
          "s": "#WIP",
          "as": "1.73%",
          "sh": "31,307"
        }
      },
      {
        "rank": 23,
        "symbol": "#PGHY",
        "name": "Invesco Global ex-US High Yield Corporate Bond ETF",
        "weight_pct": 1.7,
        "shares": 61760,
        "raw": {
          "no": 23,
          "n": "Invesco Global ex-US High Yield Corporate Bond ETF",
          "s": "#PGHY",
          "as": "1.70%",
          "sh": "61,760"
        }
      },
      {
        "rank": 24,
        "symbol": "#VCSH",
        "name": "Vanguard Short-Term Corporate Bond ETF",
        "weight_pct": 1.67,
        "shares": 15335,
        "raw": {
          "no": 24,
          "n": "Vanguard Short-Term Corporate Bond ETF",
          "s": "#VCSH",
          "as": "1.67%",
          "sh": "15,335"
        }
      },
      {
        "rank": 25,
        "symbol": "#VGIT",
        "name": "Vanguard Intermediate-Term Treasury ETF",
        "weight_pct": 1.65,
        "shares": 20367,
        "raw": {
          "no": 25,
          "n": "Vanguard Intermediate-Term Treasury ETF",
          "s": "#VGIT",
          "as": "1.65%",
          "sh": "20,367"
        }
      }
    ],
    "asset_allocation": null,
    "sectors": null,
    "countries": [
      {
        "code": "US",
        "weight": 41.68276,
        "country": "United States"
      },
      {
        "code": "JP",
        "weight": 5.55,
        "country": "Japan"
      },
      {
        "code": "CN",
        "weight": 5.42545,
        "country": "China"
      },
      {
        "code": "CA",
        "weight": 4.07274,
        "country": "Canada"
      },
      {
        "code": "GB",
        "weight": 3.8276,
        "country": "United Kingdom"
      },
      {
        "code": "TW",
        "weight": 3.57461,
        "country": "Taiwan"
      },
      {
        "code": "KR",
        "weight": 3.20405,
        "country": "Korea"
      },
      {
        "code": "ZA",
        "weight": 3.16325,
        "country": "South Africa"
      },
      {
        "code": "TR",
        "weight": 2.68913,
        "country": "Turkey"
      },
      {
        "code": "BR",
        "weight": 2.38832,
        "country": "Brazil"
      },
      {
        "code": "PL",
        "weight": 2.22583,
        "country": "Poland"
      },
      {
        "code": "CZ",
        "weight": 1.79444,
        "country": "Czechia"
      },
      {
        "code": "SG",
        "weight": 1.7618,
        "country": "Singapore"
      },
      {
        "code": "CO",
        "weight": 1.63324,
        "country": "Colombia"
      },
      {
        "code": "HK",
        "weight": 1.5775,
        "country": "Hong Kong"
      },
      {
        "code": "FR",
        "weight": 1.49722,
        "country": "France"
      },
      {
        "code": "AT",
        "weight": 1.32433,
        "country": "Austria"
      },
      {
        "code": "TH",
        "weight": 1.30668,
        "country": "Thailand"
      },
      {
        "code": "DE",
        "weight": 1.29554,
        "country": "Germany"
      },
      {
        "code": "AU",
        "weight": 1.24108,
        "country": "Australia"
      },
      {
        "code": "NL",
        "weight": 1.17726,
        "country": "Netherlands"
      },
      {
        "code": "CL",
        "weight": 1.16444,
        "country": "Chile"
      },
      {
        "code": "IN",
        "weight": 0.84836,
        "country": "India"
      },
      {
        "code": "IT",
        "weight": 0.82823,
        "country": "Italy"
      },
      {
        "code": "NO",
        "weight": 0.7957,
        "country": "Norway"
      },
      {
        "code": "GR",
        "weight": 0.75593,
        "country": "Greece"
      },
      {
        "code": "MX",
        "weight": 0.45956,
        "country": "Mexico"
      },
      {
        "code": "ES",
        "weight": 0.39499,
        "country": "Spain"
      },
      {
        "code": "IL",
        "weight": 0.37613,
        "country": "Israel"
      },
      {
        "code": "CH",
        "weight": 0.35114,
        "country": "Switzerland"
      },
      {
        "code": "BE",
        "weight": 0.31782,
        "country": "Belgium"
      },
      {
        "code": "DK",
        "weight": 0.2547,
        "country": "Denmark"
      },
      {
        "code": "SE",
        "weight": 0.19871,
        "country": "Sweden"
      },
      {
        "code": "ID",
        "weight": 0.19404,
        "country": "Indonesia"
      },
      {
        "code": "HU",
        "weight": 0.17264,
        "country": "Hungary"
      },
      {
        "code": "IE",
        "weight": 0.12351,
        "country": "Ireland"
      },
      {
        "code": "PT",
        "weight": 0.0885,
        "country": "Portugal"
      },
      {
        "code": "PE",
        "weight": 0.03654,
        "country": "Peru"
      }
    ],
    "classification": {
      "is_leveraged": false,
      "leverage_factor": null,
      "is_inverse": false,
      "is_single_stock": false,
      "underlying": null,
      "source": "stockanalysis.overview.description",
      "confidence": "high"
    },
    "yahoo_funds_data_available": false
  },
  "financials": null,
  "sources": {
    "yf": false,
    "stockanalysis": true,
    "stockanalysis_yf_fallback": false,
    "stockanalysis_etf_catalog": true,
    "slickcharts": false
  },
  "source_files": {
    "yf": null,
    "stockanalysis": "stockanalysis/etfs/GAA.json",
    "stockanalysis_yf_fallback": null,
    "stockanalysis_etf_catalog": "stockanalysis/surfaces/etf_screener.json",
    "slickcharts": null
  },
  "resolver": {
    "version": "market-facts-resolver/v1",
    "field_source_policy": {
      "price": [
        "yf",
        "yf.fast_info",
        "stockanalysis.quote",
        "yf.stockanalysis_fallback.quote",
        "slickcharts"
      ],
      "previous_close": [
        "yf",
        "stockanalysis.quote",
        "yf.stockanalysis_fallback.quote"
      ],
      "change": [
        "stockanalysis.quote",
        "yf",
        "yf.derived",
        "yf.stockanalysis_fallback.quote"
      ],
      "change_pct": [
        "stockanalysis.quote",
        "yf",
        "yf.derived",
        "yf.stockanalysis_fallback.quote"
      ],
      "market_cap": [
        "yf",
        "stockanalysis.overview",
        "slickcharts"
      ],
      "total_assets": [
        "yf",
        "stockanalysis.overview",
        "yf.stockanalysis_fallback.overview"
      ],
      "trailing_pe": [
        "yf",
        "slickcharts"
      ],
      "forward_pe": [
        "yf",
        "stockanalysis.overview",
        "yf.stockanalysis_fallback.overview",
        "slickcharts"
      ],
      "dividend_yield": [
        "yf",
        "stockanalysis.overview",
        "yf.stockanalysis_fallback.overview",
        "slickcharts"
      ],
      "beta": [
        "yf",
        "stockanalysis.overview",
        "yf.stockanalysis_fallback.overview"
      ],
      "expense_ratio": [
        "yf",
        "stockanalysis.overview",
        "yf.stockanalysis_fallback.overview"
      ],
      "return_1m": [
        "yf.history_1y",
        "stockanalysis.detail.performance",
        "stockanalysis.etf_screener.performance",
        "stockanalysis.etf_universe.performance"
      ],
      "return_3m": [
        "yf.history_1y",
        "stockanalysis.detail.history"
      ],
      "return_ytd": [
        "yf.history_1y",
        "stockanalysis.detail.performance",
        "stockanalysis.etf_screener.performance",
        "stockanalysis.etf_universe.performance",
        "yf"
      ],
      "return_1y": [
        "yf.history_1y",
        "stockanalysis.detail.performance",
        "stockanalysis.etf_screener.performance",
        "stockanalysis.etf_universe.performance",
        "yf"
      ],
      "return_3y_avg": [
        "yf",
        "stockanalysis.detail.history"
      ],
      "return_5y_avg": [
        "yf",
        "stockanalysis.detail.performance",
        "stockanalysis.etf_screener.performance",
        "stockanalysis.etf_universe.performance"
      ],
      "return_10y_avg": [
        "stockanalysis.detail.performance",
        "stockanalysis.etf_screener.performance",
        "stockanalysis.etf_universe.performance"
      ],
      "return_max_avg": [
        "stockanalysis.detail.performance",
        "stockanalysis.etf_screener.performance",
        "stockanalysis.etf_universe.performance"
      ]
    },
    "principle": "Preserve all non-null overlapping source candidates while exposing the selected value at facts.{field}.value."
  }
}
