{
  "schema_version": "market-facts/v1",
  "ticker": "PEX",
  "asset_type": "etf",
  "generated_at": "2026-06-21T00:42:40Z",
  "identity": {
    "name": "PEX",
    "exchange": null,
    "currency": null,
    "sector": null,
    "industry": null,
    "fund_family": null,
    "category": null
  },
  "facts": {
    "price": {
      "value": 21.7038,
      "source": "stockanalysis.quote",
      "as_of": null,
      "fetched_at": "2026-06-19T09:32:28Z",
      "confidence": "observed",
      "policy": [
        "yf",
        "yf.fast_info",
        "stockanalysis.quote",
        "yf.stockanalysis_fallback.quote",
        "slickcharts"
      ],
      "candidates": [
        {
          "value": 21.7038,
          "source": "stockanalysis.quote",
          "as_of": null,
          "fetched_at": "2026-06-19T09:32:28Z",
          "confidence": "observed"
        }
      ],
      "candidate_count": 1
    },
    "previous_close": {
      "value": 21.7,
      "source": "stockanalysis.quote",
      "as_of": null,
      "fetched_at": "2026-06-19T09:32:28Z",
      "confidence": "observed",
      "policy": [
        "yf",
        "stockanalysis.quote",
        "yf.stockanalysis_fallback.quote"
      ],
      "candidates": [
        {
          "value": 21.7,
          "source": "stockanalysis.quote",
          "as_of": null,
          "fetched_at": "2026-06-19T09:32:28Z",
          "confidence": "observed"
        }
      ],
      "candidate_count": 1
    },
    "change": {
      "value": 0.02,
      "source": "stockanalysis.quote",
      "as_of": null,
      "fetched_at": "2026-06-19T09:32:28Z",
      "confidence": "observed",
      "policy": [
        "stockanalysis.quote",
        "yf",
        "yf.derived",
        "yf.stockanalysis_fallback.quote"
      ],
      "candidates": [
        {
          "value": 0.02,
          "source": "stockanalysis.quote",
          "as_of": null,
          "fetched_at": "2026-06-19T09:32:28Z",
          "confidence": "observed"
        }
      ],
      "candidate_count": 1
    },
    "change_pct": {
      "value": 0.11,
      "source": "stockanalysis.quote",
      "as_of": null,
      "fetched_at": "2026-06-19T09:32:28Z",
      "confidence": "observed",
      "policy": [
        "stockanalysis.quote",
        "yf",
        "yf.derived",
        "yf.stockanalysis_fallback.quote"
      ],
      "candidates": [
        {
          "value": 0.11,
          "source": "stockanalysis.quote",
          "as_of": null,
          "fetched_at": "2026-06-19T09:32:28Z",
          "confidence": "observed"
        }
      ],
      "candidate_count": 1
    },
    "total_assets": {
      "value": 11070000.0,
      "source": "stockanalysis.overview",
      "as_of": null,
      "fetched_at": "2026-06-19T09:32:28Z",
      "confidence": "observed",
      "policy": [
        "yf",
        "stockanalysis.overview",
        "yf.stockanalysis_fallback.overview"
      ],
      "candidates": [
        {
          "value": 11070000.0,
          "source": "stockanalysis.overview",
          "as_of": null,
          "fetched_at": "2026-06-19T09:32:28Z",
          "confidence": "observed"
        }
      ],
      "candidate_count": 1
    },
    "dividend_yield": {
      "value": 12.76,
      "source": "stockanalysis.overview",
      "as_of": null,
      "fetched_at": "2026-06-19T09:32:28Z",
      "confidence": "observed",
      "unit": "percent_points",
      "policy": [
        "yf",
        "stockanalysis.overview",
        "yf.stockanalysis_fallback.overview",
        "slickcharts"
      ],
      "candidates": [
        {
          "value": 12.76,
          "source": "stockanalysis.overview",
          "as_of": null,
          "fetched_at": "2026-06-19T09:32:28Z",
          "confidence": "observed",
          "unit": "percent_points"
        }
      ],
      "candidate_count": 1
    },
    "beta": {
      "value": 0.91,
      "source": "stockanalysis.overview",
      "as_of": null,
      "fetched_at": "2026-06-19T09:32:28Z",
      "confidence": "observed",
      "policy": [
        "yf",
        "stockanalysis.overview",
        "yf.stockanalysis_fallback.overview"
      ],
      "candidates": [
        {
          "value": 0.91,
          "source": "stockanalysis.overview",
          "as_of": null,
          "fetched_at": "2026-06-19T09:32:28Z",
          "confidence": "observed"
        }
      ],
      "candidate_count": 1
    },
    "expense_ratio": {
      "value": 2.95,
      "source": "stockanalysis.overview",
      "as_of": null,
      "fetched_at": "2026-06-19T09:32:28Z",
      "confidence": "observed",
      "unit": "percent_points",
      "policy": [
        "yf",
        "stockanalysis.overview",
        "yf.stockanalysis_fallback.overview"
      ],
      "candidates": [
        {
          "value": 2.95,
          "source": "stockanalysis.overview",
          "as_of": null,
          "fetched_at": "2026-06-19T09:32:28Z",
          "confidence": "observed",
          "unit": "percent_points"
        }
      ],
      "candidate_count": 1
    },
    "return_1m": {
      "value": -0.10999783686261128,
      "source": "stockanalysis.detail.performance",
      "as_of": null,
      "fetched_at": "2026-06-19T09:32:28Z",
      "confidence": "observed",
      "unit": "percent_points",
      "policy": [
        "yf.history_1y",
        "stockanalysis.detail.performance",
        "stockanalysis.etf_screener.performance",
        "stockanalysis.etf_universe.performance"
      ],
      "candidates": [
        {
          "value": -0.10999783686261128,
          "source": "stockanalysis.detail.performance",
          "as_of": null,
          "fetched_at": "2026-06-19T09:32:28Z",
          "confidence": "observed",
          "unit": "percent_points"
        },
        {
          "value": -0.10999783686261128,
          "source": "stockanalysis.etf_screener.performance",
          "as_of": null,
          "fetched_at": "2026-06-17T14:00:25Z",
          "confidence": "observed",
          "unit": "percent_points"
        }
      ],
      "candidate_count": 2
    },
    "return_3m": {
      "value": 0.058198780923645686,
      "source": "stockanalysis.detail.history",
      "as_of": "2026-06-18",
      "fetched_at": "2026-06-19T09:32:28Z",
      "confidence": "derived",
      "unit": "percent_points",
      "policy": [
        "yf.history_1y",
        "stockanalysis.detail.history"
      ],
      "candidates": [
        {
          "value": 0.058198780923645686,
          "source": "stockanalysis.detail.history",
          "as_of": "2026-06-18",
          "fetched_at": "2026-06-19T09:32:28Z",
          "confidence": "derived",
          "unit": "percent_points"
        }
      ],
      "candidate_count": 1
    },
    "return_ytd": {
      "value": -12.099641951780145,
      "source": "stockanalysis.detail.performance",
      "as_of": null,
      "fetched_at": "2026-06-19T09:32:28Z",
      "confidence": "observed",
      "unit": "percent_points",
      "policy": [
        "yf.history_1y",
        "stockanalysis.detail.performance",
        "stockanalysis.etf_screener.performance",
        "stockanalysis.etf_universe.performance",
        "yf"
      ],
      "candidates": [
        {
          "value": -12.099641951780145,
          "source": "stockanalysis.detail.performance",
          "as_of": null,
          "fetched_at": "2026-06-19T09:32:28Z",
          "confidence": "observed",
          "unit": "percent_points"
        },
        {
          "value": -12.099641951780145,
          "source": "stockanalysis.etf_screener.performance",
          "as_of": null,
          "fetched_at": "2026-06-17T14:00:25Z",
          "confidence": "observed",
          "unit": "percent_points"
        }
      ],
      "candidate_count": 2
    },
    "return_1y": {
      "value": -12.352371911083198,
      "source": "stockanalysis.detail.performance",
      "as_of": null,
      "fetched_at": "2026-06-19T09:32:28Z",
      "confidence": "observed",
      "unit": "percent_points",
      "policy": [
        "yf.history_1y",
        "stockanalysis.detail.performance",
        "stockanalysis.etf_screener.performance",
        "stockanalysis.etf_universe.performance",
        "yf"
      ],
      "candidates": [
        {
          "value": -12.352371911083198,
          "source": "stockanalysis.detail.performance",
          "as_of": null,
          "fetched_at": "2026-06-19T09:32:28Z",
          "confidence": "observed",
          "unit": "percent_points"
        },
        {
          "value": -12.352371911083198,
          "source": "stockanalysis.etf_screener.performance",
          "as_of": null,
          "fetched_at": "2026-06-17T14:00:25Z",
          "confidence": "observed",
          "unit": "percent_points"
        }
      ],
      "candidate_count": 2
    },
    "return_3y_avg": {
      "value": -1.4339501541927646,
      "source": "stockanalysis.detail.history",
      "as_of": "2026-06-01",
      "fetched_at": "2026-06-19T09:32:28Z",
      "confidence": "derived",
      "unit": "percent_points",
      "policy": [
        "yf",
        "stockanalysis.detail.history"
      ],
      "candidates": [
        {
          "value": -1.4339501541927646,
          "source": "stockanalysis.detail.history",
          "as_of": "2026-06-01",
          "fetched_at": "2026-06-19T09:32:28Z",
          "confidence": "derived",
          "unit": "percent_points"
        }
      ],
      "candidate_count": 1
    },
    "return_5y_avg": {
      "value": -0.7737333259656753,
      "source": "stockanalysis.detail.performance",
      "as_of": null,
      "fetched_at": "2026-06-19T09:32:28Z",
      "confidence": "observed",
      "unit": "percent_points",
      "policy": [
        "yf",
        "stockanalysis.detail.performance",
        "stockanalysis.etf_screener.performance",
        "stockanalysis.etf_universe.performance"
      ],
      "candidates": [
        {
          "value": -0.7737333259656753,
          "source": "stockanalysis.detail.performance",
          "as_of": null,
          "fetched_at": "2026-06-19T09:32:28Z",
          "confidence": "observed",
          "unit": "percent_points"
        },
        {
          "value": -0.7737333259656753,
          "source": "stockanalysis.etf_screener.performance",
          "as_of": null,
          "fetched_at": "2026-06-17T14:00:25Z",
          "confidence": "observed",
          "unit": "percent_points"
        }
      ],
      "candidate_count": 2
    },
    "return_10y_avg": {
      "value": 4.623,
      "source": "stockanalysis.detail.performance",
      "as_of": null,
      "fetched_at": "2026-06-19T09:32:28Z",
      "confidence": "observed",
      "unit": "percent_points",
      "policy": [
        "stockanalysis.detail.performance",
        "stockanalysis.etf_screener.performance",
        "stockanalysis.etf_universe.performance"
      ],
      "candidates": [
        {
          "value": 4.623,
          "source": "stockanalysis.detail.performance",
          "as_of": null,
          "fetched_at": "2026-06-19T09:32:28Z",
          "confidence": "observed",
          "unit": "percent_points"
        },
        {
          "value": 4.623,
          "source": "stockanalysis.etf_screener.performance",
          "as_of": null,
          "fetched_at": "2026-06-17T14:00:25Z",
          "confidence": "observed",
          "unit": "percent_points"
        }
      ],
      "candidate_count": 2
    },
    "return_max_avg": {
      "value": 4.904,
      "source": "stockanalysis.detail.performance",
      "as_of": null,
      "fetched_at": "2026-06-19T09:32:28Z",
      "confidence": "observed",
      "unit": "percent_points",
      "policy": [
        "stockanalysis.detail.performance",
        "stockanalysis.etf_screener.performance",
        "stockanalysis.etf_universe.performance"
      ],
      "candidates": [
        {
          "value": 4.904,
          "source": "stockanalysis.detail.performance",
          "as_of": null,
          "fetched_at": "2026-06-19T09:32:28Z",
          "confidence": "observed",
          "unit": "percent_points"
        },
        {
          "value": 4.904,
          "source": "stockanalysis.etf_screener.performance",
          "as_of": null,
          "fetched_at": "2026-06-17T14:00:25Z",
          "confidence": "observed",
          "unit": "percent_points"
        }
      ],
      "candidate_count": 2
    }
  },
  "etf": {
    "holdings_count": 31,
    "holdings_updated": "Jun 16, 2026",
    "top_holdings": [
      {
        "rank": 1,
        "symbol": "ARCC",
        "name": "Ares Capital Corporation",
        "weight_pct": 10.04,
        "shares": 59703,
        "raw": {
          "no": 1,
          "n": "Ares Capital Corporation",
          "s": "$ARCC",
          "as": "10.04%",
          "sh": "59,703"
        }
      },
      {
        "rank": 2,
        "symbol": "!LON/III",
        "name": "3i Group plc",
        "weight_pct": 8.81,
        "shares": 31278,
        "raw": {
          "no": 2,
          "n": "3i Group plc",
          "s": "!lon/III",
          "as": "8.81%",
          "sh": "31,278"
        }
      },
      {
        "rank": 3,
        "symbol": "!TSX/ONEX",
        "name": "Onex Corporation",
        "weight_pct": 8.53,
        "shares": 11927,
        "raw": {
          "no": 3,
          "n": "Onex Corporation",
          "s": "!tsx/ONEX",
          "as": "8.53%",
          "sh": "11,927"
        }
      },
      {
        "rank": 4,
        "symbol": "!EBR/SOF",
        "name": "Sofina Société Anonyme",
        "weight_pct": 7.15,
        "shares": 3105,
        "raw": {
          "no": 4,
          "n": "Sofina Société Anonyme",
          "s": "!ebr/SOF",
          "as": "7.15%",
          "sh": "3,105"
        }
      },
      {
        "rank": 5,
        "symbol": "MAIN",
        "name": "Main Street Capital Corporation",
        "weight_pct": 7.11,
        "shares": 15289,
        "raw": {
          "no": 5,
          "n": "Main Street Capital Corporation",
          "s": "$MAIN",
          "as": "7.11%",
          "sh": "15,289"
        }
      },
      {
        "rank": 6,
        "symbol": "HTGC",
        "name": "Hercules Capital, Inc.",
        "weight_pct": 4.53,
        "shares": 32073,
        "raw": {
          "no": 6,
          "n": "Hercules Capital, Inc.",
          "s": "$HTGC",
          "as": "4.53%",
          "sh": "32,073"
        }
      },
      {
        "rank": 7,
        "symbol": "GBDC",
        "name": "Golub Capital BDC, Inc.",
        "weight_pct": 4.36,
        "shares": 37797,
        "raw": {
          "no": 7,
          "n": "Golub Capital BDC, Inc.",
          "s": "$GBDC",
          "as": "4.36%",
          "sh": "37,797"
        }
      },
      {
        "rank": 8,
        "symbol": "FSK",
        "name": "FS KKR Capital Corp.",
        "weight_pct": 4.3,
        "shares": 46010,
        "raw": {
          "no": 8,
          "n": "FS KKR Capital Corp.",
          "s": "$FSK",
          "as": "4.30%",
          "sh": "46,010"
        }
      },
      {
        "rank": 9,
        "symbol": "!EPA/MF",
        "name": "Wendel",
        "weight_pct": 4.0,
        "shares": 4488,
        "raw": {
          "no": 9,
          "n": "Wendel",
          "s": "!epa/MF",
          "as": "4.00%",
          "sh": "4,488"
        }
      },
      {
        "rank": 10,
        "symbol": "!EPA/RF",
        "name": "Eurazeo SE",
        "weight_pct": 3.9,
        "shares": 8420,
        "raw": {
          "no": 10,
          "n": "Eurazeo SE",
          "s": "!epa/RF",
          "as": "3.90%",
          "sh": "8,420"
        }
      },
      {
        "rank": 11,
        "symbol": "!LON/HGT",
        "name": "HgCapital Trust plc",
        "weight_pct": 3.8,
        "shares": 79975,
        "raw": {
          "no": 11,
          "n": "HgCapital Trust plc",
          "s": "!lon/HGT",
          "as": "3.80%",
          "sh": "79,975"
        }
      },
      {
        "rank": 12,
        "symbol": "!SWX/HBMN",
        "name": "HBM Healthcare Investments AG",
        "weight_pct": 2.78,
        "shares": 1056,
        "raw": {
          "no": 12,
          "n": "HBM Healthcare Investments AG",
          "s": "!swx/HBMN",
          "as": "2.78%",
          "sh": "1,056"
        }
      },
      {
        "rank": 13,
        "symbol": "TSLX",
        "name": "Sixth Street Specialty Lending, Inc.",
        "weight_pct": 2.65,
        "shares": 17683,
        "raw": {
          "no": 13,
          "n": "Sixth Street Specialty Lending, Inc.",
          "s": "$TSLX",
          "as": "2.65%",
          "sh": "17,683"
        }
      },
      {
        "rank": 14,
        "symbol": "!STO/KINV.B",
        "name": "Kinnevik AB",
        "weight_pct": 2.47,
        "shares": 45774,
        "raw": {
          "no": 14,
          "n": "Kinnevik AB",
          "s": "!sto/KINV.B",
          "as": "2.47%",
          "sh": "45,774"
        }
      },
      {
        "rank": 15,
        "symbol": "CSWC",
        "name": "Capital Southwest Corporation",
        "weight_pct": 2.38,
        "shares": 11364,
        "raw": {
          "no": 15,
          "n": "Capital Southwest Corporation",
          "s": "$CSWC",
          "as": "2.38%",
          "sh": "11,364"
        }
      },
      {
        "rank": 16,
        "symbol": "!LON/GROW",
        "name": "Molten Ventures Plc",
        "weight_pct": 2.29,
        "shares": 30807,
        "raw": {
          "no": 16,
          "n": "Molten Ventures Plc",
          "s": "!lon/GROW",
          "as": "2.29%",
          "sh": "30,807"
        }
      },
      {
        "rank": 17,
        "symbol": "!EBR/GIMB",
        "name": "Gimv NV",
        "weight_pct": 2.17,
        "shares": 4581,
        "raw": {
          "no": 17,
          "n": "Gimv NV",
          "s": "!ebr/GIMB",
          "as": "2.17%",
          "sh": "4,581"
        }
      },
      {
        "rank": 18,
        "symbol": "OCSL",
        "name": "Oaktree Specialty Lending Corporation",
        "weight_pct": 1.79,
        "shares": 16710,
        "raw": {
          "no": 18,
          "n": "Oaktree Specialty Lending Corporation",
          "s": "$OCSL",
          "as": "1.79%",
          "sh": "16,710"
        }
      },
      {
        "rank": 19,
        "symbol": "GSBD",
        "name": "Goldman Sachs BDC, Inc.",
        "weight_pct": 1.72,
        "shares": 20491,
        "raw": {
          "no": 19,
          "n": "Goldman Sachs BDC, Inc.",
          "s": "$GSBD",
          "as": "1.72%",
          "sh": "20,491"
        }
      },
      {
        "rank": 20,
        "symbol": "!LON/OCI",
        "name": "Oakley Capital Investments Limited",
        "weight_pct": 1.58,
        "shares": 25456,
        "raw": {
          "no": 20,
          "n": "Oakley Capital Investments Limited",
          "s": "!lon/OCI",
          "as": "1.58%",
          "sh": "25,456"
        }
      },
      {
        "rank": 21,
        "symbol": "MFIC",
        "name": "MidCap Financial Investment Corporation",
        "weight_pct": 1.57,
        "shares": 17245,
        "raw": {
          "no": 21,
          "n": "MidCap Financial Investment Corporation",
          "s": "$MFIC",
          "as": "1.57%",
          "sh": "17,245"
        }
      },
      {
        "rank": 22,
        "symbol": "PSEC",
        "name": "Prospect Capital Corporation",
        "weight_pct": 1.4,
        "shares": 69007,
        "raw": {
          "no": 22,
          "n": "Prospect Capital Corporation",
          "s": "$PSEC",
          "as": "1.40%",
          "sh": "69,007"
        }
      },
      {
        "rank": 23,
        "symbol": "!LON/SYNC",
        "name": "Syncona Limited",
        "weight_pct": 1.37,
        "shares": 116783,
        "raw": {
          "no": 23,
          "n": "Syncona Limited",
          "s": "!lon/SYNC",
          "as": "1.37%",
          "sh": "116,783"
        }
      },
      {
        "rank": 24,
        "symbol": "!LON/NBPE",
        "name": "Neuberger Private Equity Partners Limited",
        "weight_pct": 1.35,
        "shares": 7590,
        "raw": {
          "no": 24,
          "n": "Neuberger Private Equity Partners Limited",
          "s": "!lon/NBPE",
          "as": "1.35%",
          "sh": "7,590"
        }
      },
      {
        "rank": 25,
        "symbol": "BBDC",
        "name": "Barings BDC, Inc.",
        "weight_pct": 1.33,
        "shares": 17499,
        "raw": {
          "no": 25,
          "n": "Barings BDC, Inc.",
          "s": "$BBDC",
          "as": "1.33%",
          "sh": "17,499"
        }
      }
    ],
    "asset_allocation": null,
    "sectors": [
      {
        "n": "Financials",
        "w": 91.15
      },
      {
        "n": "Other",
        "w": 8.85
      }
    ],
    "countries": [
      {
        "code": "US",
        "weight": 63.09373,
        "country": "United States"
      },
      {
        "code": "BE",
        "weight": 11.72143,
        "country": "Belgium"
      },
      {
        "code": "FR",
        "weight": 9.69779,
        "country": "France"
      },
      {
        "code": "CA",
        "weight": 9.13595,
        "country": "Canada"
      },
      {
        "code": "SE",
        "weight": 5.57681,
        "country": "Sweden"
      },
      {
        "code": "CN",
        "weight": 0.43524,
        "country": "China"
      },
      {
        "code": "NL",
        "weight": 0.16348,
        "country": "Netherlands"
      },
      {
        "code": "IN",
        "weight": 0.12981,
        "country": "India"
      },
      {
        "code": "CH",
        "weight": 0.03126,
        "country": "Switzerland"
      },
      {
        "code": "IL",
        "weight": 0.01209,
        "country": "Israel"
      },
      {
        "code": "DK",
        "weight": 0.0024,
        "country": "Denmark"
      }
    ],
    "classification": {
      "is_leveraged": false,
      "leverage_factor": null,
      "is_inverse": false,
      "is_single_stock": false,
      "underlying": null,
      "source": "stockanalysis.overview.description",
      "confidence": "high"
    },
    "yahoo_funds_data_available": false
  },
  "financials": null,
  "sources": {
    "yf": false,
    "stockanalysis": true,
    "stockanalysis_yf_fallback": false,
    "stockanalysis_etf_catalog": true,
    "slickcharts": false
  },
  "source_files": {
    "yf": null,
    "stockanalysis": "stockanalysis/etfs/PEX.json",
    "stockanalysis_yf_fallback": null,
    "stockanalysis_etf_catalog": "stockanalysis/surfaces/etf_screener.json",
    "slickcharts": null
  },
  "resolver": {
    "version": "market-facts-resolver/v1",
    "field_source_policy": {
      "price": [
        "yf",
        "yf.fast_info",
        "stockanalysis.quote",
        "yf.stockanalysis_fallback.quote",
        "slickcharts"
      ],
      "previous_close": [
        "yf",
        "stockanalysis.quote",
        "yf.stockanalysis_fallback.quote"
      ],
      "change": [
        "stockanalysis.quote",
        "yf",
        "yf.derived",
        "yf.stockanalysis_fallback.quote"
      ],
      "change_pct": [
        "stockanalysis.quote",
        "yf",
        "yf.derived",
        "yf.stockanalysis_fallback.quote"
      ],
      "market_cap": [
        "yf",
        "stockanalysis.overview",
        "slickcharts"
      ],
      "total_assets": [
        "yf",
        "stockanalysis.overview",
        "yf.stockanalysis_fallback.overview"
      ],
      "trailing_pe": [
        "yf",
        "slickcharts"
      ],
      "forward_pe": [
        "yf",
        "stockanalysis.overview",
        "yf.stockanalysis_fallback.overview",
        "slickcharts"
      ],
      "dividend_yield": [
        "yf",
        "stockanalysis.overview",
        "yf.stockanalysis_fallback.overview",
        "slickcharts"
      ],
      "beta": [
        "yf",
        "stockanalysis.overview",
        "yf.stockanalysis_fallback.overview"
      ],
      "expense_ratio": [
        "yf",
        "stockanalysis.overview",
        "yf.stockanalysis_fallback.overview"
      ],
      "return_1m": [
        "yf.history_1y",
        "stockanalysis.detail.performance",
        "stockanalysis.etf_screener.performance",
        "stockanalysis.etf_universe.performance"
      ],
      "return_3m": [
        "yf.history_1y",
        "stockanalysis.detail.history"
      ],
      "return_ytd": [
        "yf.history_1y",
        "stockanalysis.detail.performance",
        "stockanalysis.etf_screener.performance",
        "stockanalysis.etf_universe.performance",
        "yf"
      ],
      "return_1y": [
        "yf.history_1y",
        "stockanalysis.detail.performance",
        "stockanalysis.etf_screener.performance",
        "stockanalysis.etf_universe.performance",
        "yf"
      ],
      "return_3y_avg": [
        "yf",
        "stockanalysis.detail.history"
      ],
      "return_5y_avg": [
        "yf",
        "stockanalysis.detail.performance",
        "stockanalysis.etf_screener.performance",
        "stockanalysis.etf_universe.performance"
      ],
      "return_10y_avg": [
        "stockanalysis.detail.performance",
        "stockanalysis.etf_screener.performance",
        "stockanalysis.etf_universe.performance"
      ],
      "return_max_avg": [
        "stockanalysis.detail.performance",
        "stockanalysis.etf_screener.performance",
        "stockanalysis.etf_universe.performance"
      ]
    },
    "principle": "Preserve all non-null overlapping source candidates while exposing the selected value at facts.{field}.value."
  }
}
